karellen_pyb_plugin/__init__.py
karellen_pyb_plugin-0.0.4.dist-info/METADATA
karellen_pyb_plugin-0.0.4.dist-info/WHEEL
karellen_pyb_plugin-0.0.4.dist-info/namespace_packages.txt
karellen_pyb_plugin-0.0.4.dist-info/top_level.txt
karellen_pyb_plugin-0.0.4.dist-info/zip-safe
karellen_pyb_plugin-0.0.4.dist-info/RECORD
