Metadata-Version: 2.1
Name: karellen-pyb-plugin
Version: 0.0.4
Summary: Karellen PyBuilder Plugin
Home-page: https://github.com/karellen/karellen-pyb-plugin
Author: Karellen, Inc
Author-email: supervisor@karellen.co
Maintainer: Arcadiy Ivanov
Maintainer-email: arcadiy@karellen.co
License: Apache License, Version 2.0
Project-URL: Bug Tracker, https://github.com/karellen/karellen-pyb-plugin/issues
Project-URL: Documentation, https://github.com/karellen/karellen-pyb-plugin/
Project-URL: Source Code, https://github.com/karellen/karellen-pyb-plugin/
Platform: UNKNOWN
Classifier: Development Status :: 5 - Production/Stable
Classifier: Environment :: Console
Classifier: Intended Audience :: Developers
Classifier: License :: OSI Approved :: Apache Software License
Classifier: Programming Language :: Python
